src/omnifuel-sdk/__init__.py
omnifuel-0.0.1.dist-info/METADATA
omnifuel-0.0.1.dist-info/WHEEL
omnifuel-0.0.1.dist-info/licenses/LICENSE
omnifuel-0.0.1.dist-info/RECORD
