Metadata-Version: 2.1
Name: omnifuel
Version: 0.0.1
Summary: Omnifuel SDK
Author-email: Adileo Barone <adileob@gmail.com>
License-File: LICENSE
Requires-Python: >=3.12
